app/__init__.py
app/cli.py
app/core/__init__.py
app/core/analytics.py
app/core/compliance.py
app/core/engine.py
app/core/spintax.py
app/core/telethon_client.py
app/core/throttler.py
app/gui/__init__.py
app/gui/main.py
app/gui/theme.py
app/gui/widgets/__init__.py
app/gui/widgets/about_widget.py
app/gui/widgets/account_widget.py
app/gui/widgets/campaign_widget.py
app/gui/widgets/log_widget.py
app/gui/widgets/recipient_widget.py
app/gui/widgets/settings_widget.py
app/gui/widgets/template_widget.py
app/gui/widgets/testing_widget.py
app/models/__init__.py
app/models/account.py
app/models/base.py
app/models/campaign.py
app/models/recipient.py
app/models/send_log.py
app/models/template.py
app/services/__init__.py
app/services/campaign_manager.py
app/services/db.py
app/services/logger.py
app/services/settings.py
app/services/translation.py
app/services/warmup_manager.py
app/translations/ca.json
app/translations/de.json
app/translations/en.json
app/translations/es.json
app/translations/et.json
app/translations/eu.json
app/translations/fr.json
app/translations/gl.json
app/translations/ja.json
app/translations/ko.json
app/translations/pt.json
app/translations/ru.json
app/translations/zh.json
app/utils/__init__.py
app/utils/crypto.py
app/utils/files.py
app/utils/windows_startup.py
telegram_multi_account_sender-1.2.3.data/data/example_files/README.md
telegram_multi_account_sender-1.2.3.data/data/example_files/accounts_example.csv
telegram_multi_account_sender-1.2.3.data/data/example_files/campaigns_example.csv
telegram_multi_account_sender-1.2.3.data/data/example_files/configurations.md
telegram_multi_account_sender-1.2.3.data/data/example_files/env_template.txt
telegram_multi_account_sender-1.2.3.data/data/example_files/recipients_example.csv
telegram_multi_account_sender-1.2.3.data/data/example_files/sample_media_urls.txt
telegram_multi_account_sender-1.2.3.data/data/example_files/spintax_examples.txt
telegram_multi_account_sender-1.2.3.dist-info/licenses/LICENSE
telegram_multi_account_sender-1.2.3.dist-info/METADATA
telegram_multi_account_sender-1.2.3.dist-info/WHEEL
telegram_multi_account_sender-1.2.3.dist-info/entry_points.txt
telegram_multi_account_sender-1.2.3.dist-info/top_level.txt
telegram_multi_account_sender-1.2.3.dist-info/RECORD
