Metadata-Version: 2.4
Name: telegram-multi-account-sender
Version: 1.2.3
Summary: Professional-grade desktop application for managing and sending messages across multiple Telegram accounts
Home-page: https://github.com/VoxHash/Telegram-Multi-Account-Message-Sender
Download-URL: https://github.com/VoxHash/Telegram-Multi-Account-Message-Sender/archive/v1.2.3.tar.gz
Author: VoxHash
Author-email: VoxHash <contact@voxhash.dev>
Maintainer: VoxHash
Maintainer-email: VoxHash <contact@voxhash.dev>
License: BSD 3-Clause License
Project-URL: Homepage, https://github.com/VoxHash/Telegram-Multi-Account-Message-Sender
Project-URL: Documentation, https://github.com/VoxHash/Telegram-Multi-Account-Message-Sender/wiki
Project-URL: Repository, https://github.com/VoxHash/Telegram-Multi-Account-Message-Sender
Project-URL: Bug Tracker, https://github.com/VoxHash/Telegram-Multi-Account-Message-Sender/issues
Project-URL: Changelog, https://github.com/VoxHash/Telegram-Multi-Account-Message-Sender/blob/main/CHANGELOG.md
Project-URL: Download, https://github.com/VoxHash/Telegram-Multi-Account-Message-Sender/releases
Project-URL: Source Code, https://github.com/VoxHash/Telegram-Multi-Account-Message-Sender
Keywords: telegram,messaging,multi-account,automation,campaign,spintax,scheduling,pyqt5,desktop,gui
Platform: Windows
Platform: macOS
Platform: Linux
Classifier: Development Status :: 5 - Production/Stable
Classifier: Intended Audience :: Developers
Classifier: Intended Audience :: End Users/Desktop
Classifier: Topic :: Communications :: Chat
Classifier: Topic :: Internet :: WWW/HTTP :: Dynamic Content
Classifier: Topic :: Software Development :: Libraries :: Python Modules
Classifier: License :: OSI Approved :: BSD License
Classifier: Programming Language :: Python :: 3
Classifier: Programming Language :: Python :: 3.10
Classifier: Programming Language :: Python :: 3.11
Classifier: Programming Language :: Python :: 3.12
Classifier: Operating System :: OS Independent
Classifier: Operating System :: Microsoft :: Windows
Classifier: Operating System :: MacOS
Classifier: Operating System :: POSIX :: Linux
Classifier: Environment :: X11 Applications :: Qt
Classifier: Environment :: Win32 (MS Windows)
Classifier: Environment :: MacOS X
Provides: telegram_multi_account_sender
Requires-Python: >=3.10
License-File: LICENSE
Requires-Dist: PyQt5>=5.15.0
Requires-Dist: telethon>=1.24.0
Requires-Dist: sqlmodel>=0.0.8
Requires-Dist: pydantic>=1.10.0
Requires-Dist: pydantic-settings>=2.0.0
Requires-Dist: rich>=13.0.0
Requires-Dist: python-dotenv>=1.0.0
Requires-Dist: cryptography>=3.4.8
Requires-Dist: pillow>=9.0.0
Requires-Dist: qrcode>=7.3.0
Requires-Dist: python-dateutil>=2.8.0
Requires-Dist: pytz>=2022.1
Requires-Dist: tzdata>=2022.1
Requires-Dist: click>=8.0.0
Requires-Dist: typer>=0.7.0
Requires-Dist: colorama>=0.4.4
Requires-Dist: tqdm>=4.64.0
Requires-Dist: psutil>=5.9.0
Requires-Dist: schedule>=1.2.0
Requires-Dist: sqlalchemy>=1.4.0
Requires-Dist: alembic>=1.8.0
Requires-Dist: aiosqlite>=0.17.0
Provides-Extra: dev
Requires-Dist: pytest>=7.0.0; extra == "dev"
Requires-Dist: pytest-cov>=4.0.0; extra == "dev"
Requires-Dist: pytest-qt>=4.0.0; extra == "dev"
Requires-Dist: black>=23.0.0; extra == "dev"
Requires-Dist: isort>=5.12.0; extra == "dev"
Requires-Dist: flake8>=6.0.0; extra == "dev"
Requires-Dist: mypy>=1.0.0; extra == "dev"
Requires-Dist: pre-commit>=3.0.0; extra == "dev"
Requires-Dist: twine>=4.0.0; extra == "dev"
Requires-Dist: build>=0.10.0; extra == "dev"
Provides-Extra: docs
Requires-Dist: sphinx>=6.0.0; extra == "docs"
Requires-Dist: sphinx-rtd-theme>=1.2.0; extra == "docs"
Requires-Dist: myst-parser>=1.0.0; extra == "docs"
Dynamic: author
Dynamic: download-url
Dynamic: home-page
Dynamic: license-file
Dynamic: maintainer
Dynamic: platform
Dynamic: provides
Dynamic: requires-python
